ddt_api_calls/__init__.py
ddt_api_calls/apps.py
ddt_api_calls/panels.py
ddt_api_calls/templates/ddt_api_calls/requests.html
ddt_api_calls-0.3.2.dist-info/LICENSE
ddt_api_calls-0.3.2.dist-info/METADATA
ddt_api_calls-0.3.2.dist-info/WHEEL
ddt_api_calls-0.3.2.dist-info/top_level.txt
ddt_api_calls-0.3.2.dist-info/RECORD
