Metadata-Version: 2.1
Name: ddt-api-calls
Version: 0.3.2
Summary: A Django Debug Toolbar pannel to track calls made with requests library.
Home-page: https://github.com/maykinmedia/ddt_api_calls
Author: Maykin Media
Author-email: support@maykinmedia.nl
License: MIT
Keywords: debug,django,api,requests
Platform: UNKNOWN
Classifier: Development Status :: 3 - Alpha
Classifier: Framework :: Django
Classifier: Framework :: Django :: 2.2
Classifier: Framework :: Django :: 3.0
Classifier: Intended Audience :: Developers
Classifier: Operating System :: Unix
Classifier: Operating System :: MacOS
Classifier: Operating System :: Microsoft :: Windows
Classifier: Programming Language :: Python :: 3.6
Classifier: Programming Language :: Python :: 3.7
Classifier: Programming Language :: Python :: 3.8
Classifier: Topic :: Software Development :: Libraries :: Python Modules
Provides-Extra: tests
Provides-Extra: pep8
Provides-Extra: coverage
Provides-Extra: docs
Provides-Extra: release
